litenet
