Metadata-Version: 1.0
Name: litenet
Version: 0.3.0.1
Summary: A socket-based client messaging service.
Home-page: https://github.com/GrandMoff100/LiteNet
Author: UNKNOWN
Author-email: UNKNOWN
License: MIT LIcence
Platform: UNKNOWN
